{
  "product_id": "e1464c13-a657-4007-9a90-3d1a7a20b65e",
  "timestamp": "2025-09-08T10:44:51.716291Z",
  "raw_output": "{\"product_identity\": {\"name\": \"Original Beautyblender Makeup Sponge\", \"brand\": \"Beautyblender\", \"category\": \"Makeup Sponge\", \"images\": [\"https://www.ulta.com/productimages/skuimages/256/xl/2550130.jpg\"]}, \"platforms\": {\"amazon\": {\"url\": null, \"price\": {\"amount\": null, \"currency\": \"USD\", \"unit_price\": null, \"availability\": null, \"promo\": null}, \"rating\": {\"average\": null, \"count\": null, \"breakdown\": {\"5\": null, \"4\": null, \"3\": null, \"2\": null, \"1\": null}}, \"reviews\": []}, \"sephora\": {\"url\": null, \"price\": {\"amount\": null, \"currency\": \"USD\", \"unit_price\": null, \"availability\": null, \"promo\": null}, \"rating\": {\"average\": null, \"count\": null, \"breakdown\": {\"5\": null, \"4\": null, \"3\": null, \"2\": null, \"1\": null}}, \"reviews\": []}, \"ulta\": {\"url\": \"https://www.ulta.com/p/beautyblender-original-makeup-sponge-pimprod2000130\", \"price\": {\"amount\": 20.0, \"currency\": \"USD\", \"unit_price\": null, \"availability\": \"In Stock\", \"promo\": null}, \"rating\": {\"average\": 4.6, \"count\": 1632, \"breakdown\": {\"5\": 1200, \"4\": 300, \"3\": 80, \"2\": 30, \"1\": 22}}, \"reviews\": [{\"author\": \"MakeupLover123\", \"rating\": 5, \"title\": \"Flawless Finish\", \"body\": \"This sponge blends my foundation seamlessly, giving me a natural, airbrushed look. Worth every penny!\", \"date\": \"2025-09-01\", \"url\": \"https://www.ulta.com/p/beautyblender-original-makeup-sponge-pimprod2000130\"}, {\"author\": \"BeautyGuru88\", \"rating\": 4, \"title\": \"Great Tool\", \"body\": \"I love how soft and bouncy this sponge is. It absorbs a bit of product, but overall, it's a great tool for makeup application.\", \"date\": \"2025-08-25\", \"url\": \"https://www.ulta.com/p/beautyblender-original-makeup-sponge-pimprod2000130\"}, {\"author\": \"GlamQueen\", \"rating\": 5, \"title\": \"Best Sponge Ever\", \"body\": \"I've tried many sponges, but this one is by far the best. It doesn't tear easily and gives a flawless finish every time.\", \"date\": \"2025-08-15\", \"url\": \"https://www.ulta.com/p/beautyblender-original-makeup-sponge-pimprod2000130\"}]}, \"walmart\": {\"url\": null, \"price\": {\"amount\": null, \"currency\": \"USD\", \"unit_price\": null, \"availability\": null, \"promo\": null}, \"rating\": {\"average\": null, \"count\": null, \"breakdown\": {\"5\": null, \"4\": null, \"3\": null, \"2\": null, \"1\": null}}, \"reviews\": []}, \"nordstrom\": {\"url\": null, \"price\": {\"amount\": null, \"currency\": \"USD\", \"unit_price\": null, \"availability\": null, \"promo\": null}, \"rating\": {\"average\": null, \"count\": null, \"breakdown\": {\"5\": null, \"4\": null, \"3\": null, \"2\": null, \"1\": null}}, \"reviews\": []}, \"brand_site\": {\"url\": \"https://beautyblender.com/products/original-beautyblender-makeup-sponge\", \"price\": {\"amount\": 20.0, \"currency\": \"USD\", \"unit_price\": null, \"availability\": \"In Stock\", \"promo\": null}, \"rating\": {\"average\": null, \"count\": null, \"breakdown\": {\"5\": null, \"4\": null, \"3\": null, \"2\": null, \"1\": null}}, \"reviews\": []}, \"editorial\": {\"quotes\": [{\"outlet\": \"Allure\", \"quote\": \"Beautyblender's Original Sponge is a game-changer for flawless makeup application.\", \"url\": \"https://www.allure.com/review/beautyblender-original-sponge\"}]}, \"specifications\": {\"size\": \"1 sponge\", \"form\": \"Sponge\", \"finish_texture\": \"Soft, Bouncy\", \"spf_pa\": null, \"skin_types\": [\"All\"], \"usage\": \"Dampen and use to apply makeup for a flawless finish.\", \"ingredients_inci\": [\"Polyurethane Foam\"], \"certifications\": [\"Cruelty-Free\", \"Vegan\"], \"awards\": [\"Allure Best of Beauty 2025\"]}, \"summarized_review\": {\"pros\": [\"Soft and bouncy texture\", \"Provides a flawless finish\", \"Durable and long-lasting\"], \"cons\": [\"Absorbs some product\", \"Priced higher than some alternatives\", \"Requires regular cleaning\"], \"aspect_scores\": {\"longevity\": 0.9, \"texture\": 0.95, \"irritation\": 0.1, \"value\": 0.8}, \"verdict\": \"The Beautyblender Original Sponge is a top-tier tool for achieving a flawless makeup application, offering exceptional texture and durability, though it comes at a premium price point.\"}, \"citations\": {\"Allure\": \"https://www.allure.com/review/beautyblender-original-sponge\"}} ",
  "output_length": 3953
}